fontforge-stubs/__init__.pyi
psMat-stubs/__init__.pyi
fontforge_stubs-2025.11.10.dist-info/licenses/LICENSE
fontforge_stubs-2025.11.10.dist-info/licenses/NOTICE
fontforge_stubs-2025.11.10.dist-info/WHEEL
fontforge_stubs-2025.11.10.dist-info/METADATA
fontforge_stubs-2025.11.10.dist-info/RECORD
