Metadata-Version: 2.4
Name: fontforge-stubs
Version: 2025.11.10
Summary: Type stubs for FontForge's Python modules
Keywords: fontforge,stubs,psMat
Author: chanicpanic
License-Expression: MIT
License-File: LICENSE
License-File: NOTICE
Classifier: Development Status :: 3 - Alpha
Classifier: Intended Audience :: Developers
Classifier: Natural Language :: English
Classifier: Operating System :: OS Independent
Classifier: Programming Language :: Python :: 3
Classifier: Programming Language :: Python :: 3.10
Classifier: Programming Language :: Python :: 3.11
Classifier: Programming Language :: Python :: 3.12
Classifier: Programming Language :: Python :: 3.13
Classifier: Programming Language :: Python :: Implementation :: CPython
Classifier: Topic :: Software Development :: Documentation
Classifier: Typing :: Stubs Only
Requires-Dist: mypy ; extra == 'test'
Requires-Python: >=3.10
Project-URL: Changelog, https://github.com/chanicpanic/fontforge-stubs/blob/main/CHANGELOG.md
Project-URL: Homepage, https://github.com/chanicpanic/fontforge-stubs
Project-URL: Issues, https://github.com/chanicpanic/fontforge-stubs/issues
Project-URL: Repository, https://github.com/chanicpanic/fontforge-stubs.git
Provides-Extra: test
